mkdocs_decision_records/__init__.py
mkdocs_decision_records/_markdown_utils.py
mkdocs_decision_records/_markdown_utils_test.py
mkdocs_decision_records/plugin.py
mkdocs_decision_records/plugin_test.py
mkdocs_decision_records-2.1.3.dist-info/METADATA
mkdocs_decision_records-2.1.3.dist-info/WHEEL
mkdocs_decision_records-2.1.3.dist-info/entry_points.txt
mkdocs_decision_records-2.1.3.dist-info/licenses/LICENSE
mkdocs_decision_records-2.1.3.dist-info/RECORD
