Metadata-Version: 2.4
Name: mkdocs-decision-records
Version: 2.1.3
Summary: Manage decision records with mkdocs in a customizable and minimal fashion.
License-File: LICENSE
Author: Timo Reymann
Author-email: mail@timo-reymann.de
Requires-Python: >=3.12,<4.0
Classifier: Development Status :: 5 - Production/Stable
Classifier: Framework :: MkDocs
Classifier: Intended Audience :: Developers
Classifier: Programming Language :: Python :: 3
Classifier: Programming Language :: Python :: 3.12
Classifier: Programming Language :: Python :: 3.13
Classifier: Programming Language :: Python :: 3.14
Classifier: Topic :: Documentation
Classifier: Topic :: Software Development :: Documentation
Requires-Dist: mkdocs (>=1.4.0)
Requires-Dist: python-frontmatter (>=1.1.0,<2.0.0)
Project-URL: Bug Tracker, https://github.com/timo-reymann/mkdocs-decision-records/issues
Project-URL: Repository, https://github.com/timo-reymann/mkdocs-decision-records
